setup.py
zgtoolkit/__init__.py
zgtoolkit.egg-info/PKG-INFO
zgtoolkit.egg-info/SOURCES.txt
zgtoolkit.egg-info/dependency_links.txt
zgtoolkit.egg-info/requires.txt
zgtoolkit.egg-info/top_level.txt
zgtoolkit/dataset/__init__.py
zgtoolkit/dataset/check.py
zgtoolkit/dataset/generate.py
zgtoolkit/dataset/modify.py
zgtoolkit/dataset/parse.py
zgtoolkit/dataset/visualization.py
zgtoolkit/mm_tools/__init__.py
zgtoolkit/mm_tools/config.py
zgtoolkit/mm_tools/inference.py
zgtoolkit/mm_tools/dataset/__init__.py
zgtoolkit/mm_tools/dataset/bbox_overlaps.py
zgtoolkit/mm_tools/dataset/class_names.py
zgtoolkit/mm_tools/dataset/dataset.py
zgtoolkit/mm_tools/dataset/mean_ap.py
zgtoolkit/mm_tools/hook/__init__.py
zgtoolkit/mm_tools/hook/history.py
zgtoolkit/statistic/__init__.py
zgtoolkit/statistic/iou.py
zgtoolkit/statistic/statistic_area.py
zgtoolkit/statistic/statistic_metric.py
zgtoolkit/utils/__init__.py
zgtoolkit/utils/img.py
zgtoolkit/utils/path.py
zgtoolkit/utils/progressbar.py