Metadata-Version: 1.2
Name: zgtoolkit
Version: 0.0.25
Summary: 张港自用数据处理脚本
Home-page: UNKNOWN
Author: zg
Author-email: 1480640365@qq.com
License: UNKNOWN
Platform: UNKNOWN
Requires-Python: >=3.6
